Metadata-Version: 2.1
Name: Rilley2
Version: 0.0.3
Summary: A simple package for https://app.tea.xyz/. Example First project https://github.com/CryptoGu1/Rilley.git and third - https://github.com/CryptoGu1/Rilley1.git
Home-page: https://github.com/CryptoGu1/Rilley2.git
Author: CryptoGU1
Author-email: Kriptoairdrop9@gmail.com
Project-URL: Homepage, https://github.com/CryptoGu1/Rilley2.git
Project-URL: Source, https://github.com/CryptoGu1/Rilley2.git
Classifier: License :: OSI Approved :: MIT License
Classifier: Programming Language :: Python :: 3
Requires-Python: >=3.6
Requires-Dist: requests>=2.20.0
Requires-Dist: Rilley
